Tarea_1/Subcircuito1_gray_to_binary/src/design/module.sv
module gray_to_binary_leds (
    input  logic [3 : 0] gray,  // Entrada: Código Gray (4 bits)
    output logic [3 : 0] binary, // Salida: Código Binario (4 bits)
    output logic [3 : 0] leds // salida: leds (se usará en el constr)
);



    // Lógica combinacional para la decodificación
    always_comb begin
        // transformación de gray a binario mediante xor

        binary[3] = gray [3]; //su valor se mantiene por ser el MSB
        binary[2] = gray [3] ^ gray [2]; //Xor de la entrada MSB y la entrada 2
        binary[1] = binary [2] ^ gray [1]; //Xor del resultado anterior con la entrada del bit en la posición 1
        binary[0] = binary [1] ^ gray [0]; //xor del resultado anterior y el bit de la entrada en la posición 0

        //debido a la estructura física de la fpga se deben negar los leds con la salida
        //esto para que cuando el dipswitch este en 0000 los leds estén apagados y no encendidos.
        leds[3] = ~binary[3];
        leds[2] = ~binary[2];
        leds[1] = ~binary[1];
        leds[0] = ~binary[0];
        
    end

endmodule

Tarea_1/Subcircuito1_gray_to_binary/src/sim/tb_gray_to_binary_leds.sv

`timescale 1ns/1ps

module tb_gray_to_binary_leds;

    // Testbench signals
    logic [3:0] gray;    // Test input: Gray code
    logic [3:0] binary;  // Test output: Binary code

    // Instantiate the module under test (MUT)
    gray_to_binary_leds dut (
        .gray(gray),
        .binary(binary)
    );

    // Test stimulus
    initial begin
        // Display header
        $display("Gray Code | Binary Code ");
        $display("----------|-------------");

        // Test each Gray code and display the result
        gray = 4'b0000; #10;
        $display("%b   | %b", gray, binary);
        
        gray = 4'b0001; #10;
        $display("%b   | %b", gray, binary);
        
        gray = 4'b0011; #10;
        $display("%b   | %b", gray, binary);
        
        gray = 4'b0010; #10;
        $display("%b   | %b", gray, binary);
        
        gray = 4'b0110; #10;
        $display("%b   | %b", gray, binary);
        
        gray = 4'b0111; #10;
        $display("%b   | %b", gray, binary);
        
        gray = 4'b0101; #10;
        $display("%b   | %b", gray, binary);
        
        gray = 4'b0100; #10;
        $display("%b   | %b", gray, binary);
        
        gray = 4'b1100; #10;
        $display("%b   | %b", gray, binary);
        
        gray = 4'b1101; #10;
        $display("%b   | %b", gray, binary);
        
        gray = 4'b1111; #10;
        $display("%b   | %b", gray, binary);
        
        gray = 4'b1110; #10;
        $display("%b   | %b", gray, binary);
        
        gray = 4'b1010; #10;
        $display("%b   | %b", gray, binary);
        
        gray = 4'b1011; #10;
        $display("%b   | %b", gray, binary);
        
        gray = 4'b1001; #10;
        $display("%b   | %b", gray, binary);
        
        gray = 4'b1000; #10;
        $display("%b   | %b", gray, binary);

        $finish;  // Stop the simulation
    end

    initial begin
        $dumpfile("tb_gray_to_binary_leds.vcd");
        $dumpvars(0,tb_gray_to_binary_leds);
    end


endmodule

Tarea_1/Subcircuito1_gray_to_binary/src/build/tb_gray_to_binary_leds.vcd
$date
	Sat Aug 24 23:39:19 2024
$end
$version
	Icarus Verilog
$end
$timescale
	1ps
$end
$scope module tb_gray_to_binary_leds $end
$var wire 4 ! binary [3:0] $end
$var reg 4 " gray [3:0] $end
$scope module dut $end
$var wire 4 # gray [3:0] $end
$var reg 4 $ binary [3:0] $end
$var reg 4 % leds [3:0] $end
$upscope $end
$upscope $end
$enddefinitions $end
$comment Show the parameter values. $end
$dumpall
$end
#0
$dumpvars
b1111 %
b0 $
b0 #
b0 "
b0 !
$end
#10000
b1110 %
b1 !
b1 $
b1 "
b1 #
#20000
b1101 %
b10 !
b10 $
b11 "
b11 #
#30000
b1100 %
b11 !
b11 $
b10 "
b10 #
#40000
b1011 %
b100 !
b100 $
b110 "
b110 #
#50000
b1010 %
b101 !
b101 $
b111 "
b111 #
#60000
b1001 %
b110 !
b110 $
b101 "
b101 #
#70000
b1000 %
b111 !
b111 $
b100 "
b100 #
#80000
b111 %
b1000 !
b1000 $
b1100 "
b1100 #
#90000
b110 %
b1001 !
b1001 $
b1101 "
b1101 #
#100000
b101 %
b1010 !
b1010 $
b1111 "
b1111 #
#110000
b100 %
b1011 !
b1011 $
b1110 "
b1110 #
#120000
b11 %
b1100 !
b1100 $
b1010 "
b1010 #
#130000
b10 %
b1101 !
b1101 $
b1011 "
b1011 #
#140000
b1 %
b1110 !
b1110 $
b1001 "
b1001 #
#150000
b0 %
b1111 !
b1111 $
b1000 "
b1000 #
