Tarea_1/Subcircuito2_binary_to_7segm/src/design/module_7segm.sv
module binary_to_7segm (

    input logic [3:0] binary, //Entrada binaria
    output logic [6:0] segments // Salida BCD

);

always_comb begin
        case(binary)
            4'b0000: segments = 7'b1111110; // "0"  
            4'b0001: segments = 7'b0110000; // "1" 
            4'b0010: segments = 7'b1101101; // "2" 
            4'b0011: segments = 7'b1111001; // "3" 
            4'b0100: segments = 7'b0110011; // "4" 
            4'b0101: segments = 7'b1011011; // "5" 
            4'b0110: segments = 7'b1011111; // "6" 
            4'b0111: segments = 7'b1110000; // "7" 
            4'b1000: segments = 7'b1111111; // "8"  
            4'b1001: segments = 7'b1110011; // "9"
            default: segments = 7'b1111110; // "0" 
        endcase
end
endmodule

Tarea_1/Subcircuito2_binary_to_7segm/src/sim/tb_binary_to_7segm.sv

`timescale 1ns/1ps

module tb_binary_to_7segm;

    // Testbench signals
    logic [3:0] binary;    // Test input: Binary code
    logic [6:0] segments;  // Test output: BCD code

    binary_to_7segm dut (
        .binary(binary),
        .segments(segments)
    );

    //Test
    initial begin

        $display("Binary | BCD");
        
        binary = 4'b0000; #10;
        $display("%b   | %b", binary, segments); //"0"

        binary = 4'b0001; #10;
        $display("%b   | %b", binary, segments); //"1"

        binary = 4'b0010; #10;
        $display("%b   | %b", binary, segments); //"2"

        binary = 4'b0011; #10;
        $display("%b   | %b", binary, segments); //"3"

        binary = 4'b0100; #10;
        $display("%b   | %b", binary, segments); //"4"

        binary = 4'b0101; #10;
        $display("%b   | %b", binary, segments); //"5"

        binary = 4'b0110; #10;
        $display("%b   | %b", binary, segments); //"6"

        binary = 4'b0111; #10;
        $display("%b   | %b", binary, segments); //"7"

        binary = 4'b1000; #10;
        $display("%b   | %b", binary, segments); //"8"

        binary = 4'b1001; #10;
        $display("%b   | %b", binary, segments); //"9"

        $finish; //Stop
    end

initial begin
        $dumpfile("tb_binary_to_7segm.vcd");
        $dumpvars(0,tb_binary_to_7segm);
    end
    
endmodule

Tarea_1/Subcircuito2_binary_to_7segm/src/build/tb_binary_to_7segm.vcd
$date
	Sun Aug 25 00:07:27 2024
$end
$version
	Icarus Verilog
$end
$timescale
	1ps
$end
$scope module tb_binary_to_7segm $end
$var wire 7 ! segments [6:0] $end
$var reg 4 " binary [3:0] $end
$scope module dut $end
$var wire 4 # binary [3:0] $end
$var reg 7 $ segments [6:0] $end
$upscope $end
$upscope $end
$enddefinitions $end
$comment Show the parameter values. $end
$dumpall
$end
#0
$dumpvars
b1111110 $
b0 #
b0 "
b1111110 !
$end
#10000
b110000 !
b110000 $
b1 "
b1 #
#20000
b1101101 !
b1101101 $
b10 "
b10 #
#30000
b1111001 !
b1111001 $
b11 "
b11 #
#40000
b110011 !
b110011 $
b100 "
b100 #
#50000
b1011011 !
b1011011 $
b101 "
b101 #
#60000
b1011111 !
b1011111 $
b110 "
b110 #
#70000
b1110000 !
b1110000 $
b111 "
b111 #
#80000
b1111111 !
b1111111 $
b1000 "
b1000 #
#90000
b1110011 !
b1110011 $
b1001 "
b1001 #
