Tarea_1/gray_to_bin_7seg/src/design/module.sv
module gray_to_binary_leds (
    input  logic [3 : 0] gray,  // Entrada: Código Gray (4 bits)
    input  logic btn, // Entrada: Boton
    //entradas para facilitar la escritura de las ecuaciones booleanas
    output wire a,
    output wire b,
    output wire c,
    output wire d,
    output wire e,
    output logic [3 : 0] binary, // Salida: Código Binario (N bits)
    output logic [3 : 0] leds, // Salida: leds
    output logic uni,  // Salida : transistor unidades
    output logic dec, // Salida: transistor decenas
    //Salidas a segmentos del display
    output logic segA,
    output logic segB,
    output logic segC,
    output logic segD,
    output logic segE,
    output logic segF,
    output logic segG
    
);

    // Lógica combinacional para la decodificació
    // gray_code a binary_code usando compuertas lógicas

    assign binary[3] = gray [3];
    assign binary[2] = gray [3] ^ gray [2];
    assign binary[1] = binary [2] ^ gray [1];
    assign binary[0] = binary [1] ^ gray [0];

    //asignacion de leds de acuerdo al bit

    assign leds[3] = ~binary[3];
    assign leds[2] = ~binary[2];
    assign leds[1] = ~binary[1];
    assign leds[0] = ~binary[0];

    //Se les asigna un nuevo valor a las variables para facilitar escritura de ecuaciones booleanas

    assign a = binary[3];
    assign b = binary[2];
    assign c = binary[1];
    assign d = binary[0];
    assign e = btn;

    //Salida para controlar transistores
    assign uni = btn;
    assign dec = ~btn;

    //Ecuaciones booleanas de los 7 segmentos
    assign segA = ~((~b & ~d & ~e) | (~a & c & ~e) | (b & d & ~e) | (a & ~c & ~e)); 
    assign segB = ~((~b & ~e) | (~c & ~d & ~e) | (~a & c & d & ~e) | (a & c & e) | (a & b & ~c) | (a & ~d & ~e));
    assign segC = ~((d & ~e) | (a & c) | (a & b & e) | (~b & ~c & ~e) | (~a & b & ~e));
    assign segD = ~((~b & ~d & ~e) | (~a & ~b & c & ~e) | (b & ~c & d & ~e) | (~a & c & ~d & ~e) | (a & ~c & ~e) | (a & b & d & ~e));
    assign segE = ~((~b & ~d & ~e) | (~a & c & ~d & ~e) | (a & ~c & ~d & ~e));
    assign segF = ~((~a & b & ~c & ~e) | (a & ~b & ~c & ~e) | (a & b & c & ~e) | (~a & ~c & ~d & ~e) | (~a & b & ~d & ~e) | (a & ~b & ~d & ~e));
    assign segG = ~((~a & c & ~e) | (b & ~e) | (a & ~c & ~e));
    

endmodule

Tarea_1/gray_to_bin_7seg/src/sim/tb_gray_to_binary_leds.sv

`timescale 1ns/1ps

module tb_gray_to_binary_leds;

    // Testbench signals
    logic [3:0] gray;    // Test input: Gray code
    logic [3:0] binary;  // Test output: Binary code
    logic btn;
    logic dec;
    logic uni;
    logic segA;
    logic segB;
    logic segC;
    logic segD;
    logic segE;
    logic segF;
    logic segG;

    // Instantiate the module under test (MUT)
    gray_to_binary_leds dut (
        .gray(gray),
        .binary(binary),
        .btn(btn),
        .dec(dec),
        .uni(uni),
        .segA(segA),
        .segB(segB),
        .segC(segC),
        .segD(segD),
        .segE(segE),
        .segF(segF),
        .segG(segG)
    );

    // Test stimulus
    initial begin
        // Display header

        $display("boton no apretado");

        btn = 1'b0;
        $display (dec);
        btn = 1'b0;
        $display (uni);

        $display("boton apretado");
        btn = 1'b1;
        $display (dec);
        btn = 1'b1;
        $display (uni);

        btn = 1'b0; //modificar valor 0 o 1 para simular tocar el boton
        $display ("btn :" , btn);

        $display("Decodificación y estado de segmento");
        $display("Nota: 0 enciende los segementos"); 
        $display("Gray Code | Binary Code ");
        $display("----------|-------------");

        // Test each Gray code and display the result
        gray = 4'b0000; #10;
        $display("%b   | %b", gray, binary);
        $display ("SegA: ",segA);
        $display ("SegB: ",segB);
        $display ("SegC: ",segC);
        $display ("SegD: ",segD);
        $display ("SegE: ",segE);
        $display ("SegF: ",segF);
        $display ("SegG: ",segG);
        
        gray = 4'b0001; #10;
        $display("%b   | %b", gray, binary);
        $display ("SegA: ",segA);
        $display ("SegB: ",segB);
        $display ("SegC: ",segC);
        $display ("SegD: ",segD);
        $display ("SegE: ",segE);
        $display ("SegF: ",segF);
        $display ("SegG: ",segG);
        
        gray = 4'b0011; #10;
        $display("%b   | %b", gray, binary);
        $display ("SegA: ",segA);
        $display ("SegB: ",segB);
        $display ("SegC: ",segC);
        $display ("SegD: ",segD);
        $display ("SegE: ",segE);
        $display ("SegF: ",segF);
        $display ("SegG: ",segG);
        
        gray = 4'b0010; #10;
        $display("%b   | %b", gray, binary);
        $display ("SegA: ",segA);
        $display ("SegB: ",segB);
        $display ("SegC: ",segC);
        $display ("SegD: ",segD);
        $display ("SegE: ",segE);
        $display ("SegF: ",segF);
        $display ("SegG: ",segG);

        gray = 4'b0110; #10;
        $display("%b   | %b", gray, binary);
        $display ("SegA: ",segA);
        $display ("SegB: ",segB);
        $display ("SegC: ",segC);
        $display ("SegD: ",segD);
        $display ("SegE: ",segE);
        $display ("SegF: ",segF);
        $display ("SegG: ",segG);
        
        gray = 4'b0111; #10;
        $display("%b   | %b", gray, binary);
        $display ("SegA: ",segA);
        $display ("SegB: ",segB);
        $display ("SegC: ",segC);
        $display ("SegD: ",segD);
        $display ("SegE: ",segE);
        $display ("SegF: ",segF);
        $display ("SegG: ",segG);
        
        gray = 4'b0101; #10;
        $display("%b   | %b", gray, binary);
        $display ("SegA: ",segA);
        $display ("SegB: ",segB);
        $display ("SegC: ",segC);
        $display ("SegD: ",segD);
        $display ("SegE: ",segE);
        $display ("SegF: ",segF);
        $display ("SegG: ",segG);
        
        gray = 4'b0100; #10;
        $display("%b   | %b", gray, binary);
        $display ("SegA: ",segA);
        $display ("SegB: ",segB);
        $display ("SegC: ",segC);
        $display ("SegD: ",segD);
        $display ("SegE: ",segE);
        $display ("SegF: ",segF);
        $display ("SegG: ",segG);
        
        gray = 4'b1100; #10;
        $display("%b   | %b", gray, binary);
        $display ("SegA: ",segA);
        $display ("SegB: ",segB);
        $display ("SegC: ",segC);
        $display ("SegD: ",segD);
        $display ("SegE: ",segE);
        $display ("SegF: ",segF);
        $display ("SegG: ",segG);
        
        gray = 4'b1101; #10;
        $display("%b   | %b", gray, binary);
        $display ("SegA: ",segA);
        $display ("SegB: ",segB);
        $display ("SegC: ",segC);
        $display ("SegD: ",segD);
        $display ("SegE: ",segE);
        $display ("SegF: ",segF);
        $display ("SegG: ",segG);
        
        gray = 4'b1111; #10;
        $display("%b   | %b", gray, binary);
        $display ("SegA: ",segA);
        $display ("SegB: ",segB);
        $display ("SegC: ",segC);
        $display ("SegD: ",segD);
        $display ("SegE: ",segE);
        $display ("SegF: ",segF);
        $display ("SegG: ",segG);
        
        gray = 4'b1110; #10;
        $display("%b   | %b", gray, binary);
        $display ("SegA: ",segA);
        $display ("SegB: ",segB);
        $display ("SegC: ",segC);
        $display ("SegD: ",segD);
        $display ("SegE: ",segE);
        $display ("SegF: ",segF);
        $display ("SegG: ",segG);

        gray = 4'b1010; #10;
        $display("%b   | %b", gray, binary);
        $display ("SegA: ",segA);
        $display ("SegB: ",segB);
        $display ("SegC: ",segC);
        $display ("SegD: ",segD);
        $display ("SegE: ",segE);
        $display ("SegF: ",segF);
        $display ("SegG: ",segG);
        
        gray = 4'b1011; #10;
        $display("%b   | %b", gray, binary);
        $display ("SegA: ",segA);
        $display ("SegB: ",segB);
        $display ("SegC: ",segC);
        $display ("SegD: ",segD);
        $display ("SegE: ",segE);
        $display ("SegF: ",segF);
        $display ("SegG: ",segG);
        
        gray = 4'b1001; #10;
        $display("%b   | %b", gray, binary);
        $display ("SegA: ",segA);
        $display ("SegB: ",segB);
        $display ("SegC: ",segC);
        $display ("SegD: ",segD);
        $display ("SegE: ",segE);
        $display ("SegF: ",segF);
        $display ("SegG: ",segG);
        
        gray = 4'b1000; #10;
        $display("%b   | %b", gray, binary);
        $display ("SegA: ",segA);
        $display ("SegB: ",segB);
        $display ("SegC: ",segC);
        $display ("SegD: ",segD);
        $display ("SegE: ",segE);
        $display ("SegF: ",segF);
        $display ("SegG: ",segG);

        $finish;  // Stop the simulation
    end

    initial begin
        $dumpfile("tb_gray_to_binary_leds.vcd");
        $dumpvars(0,tb_gray_to_binary_leds);
    end


endmodule

Tarea_1/gray_to_bin_7seg/src/build/tb_gray_to_binary_leds.vcd
$date
	Sun Aug 25 17:45:24 2024
$end
$version
	Icarus Verilog
$end
$timescale
	1ps
$end
$scope module tb_gray_to_binary_leds $end
$var wire 1 ! uni $end
$var wire 1 " segG $end
$var wire 1 # segF $end
$var wire 1 $ segE $end
$var wire 1 % segD $end
$var wire 1 & segC $end
$var wire 1 ' segB $end
$var wire 1 ( segA $end
$var wire 1 ) dec $end
$var wire 4 * binary [3:0] $end
$var reg 1 + btn $end
$var reg 4 , gray [3:0] $end
$scope module dut $end
$var wire 1 + btn $end
$var wire 1 ) dec $end
$var wire 1 - e $end
$var wire 4 . gray [3:0] $end
$var wire 1 ( segA $end
$var wire 1 ' segB $end
$var wire 1 & segC $end
$var wire 1 % segD $end
$var wire 1 $ segE $end
$var wire 1 # segF $end
$var wire 1 " segG $end
$var wire 1 ! uni $end
$var wire 4 / leds [3:0] $end
$var wire 1 0 d $end
$var wire 1 1 c $end
$var wire 4 2 binary [3:0] $end
$var wire 1 3 b $end
$var wire 1 4 a $end
$upscope $end
$upscope $end
$enddefinitions $end
$comment Show the parameter values. $end
$dumpall
$end
#0
$dumpvars
04
03
b0 2
01
00
b1111 /
b0 .
0-
b0 ,
0+
b0 *
1)
0(
0'
0&
0%
0$
0#
1"
0!
$end
#10000
1%
1#
1(
1$
b1110 /
10
b1 *
b1 2
b1 ,
b1 .
#20000
0$
1&
0%
0(
0"
00
b1101 /
11
b10 *
b10 2
b11 ,
b11 .
#30000
1$
0&
b1100 /
10
b11 *
b11 2
b10 ,
b10 .
#40000
0#
1%
0'
1(
00
01
b1011 /
13
b100 *
b100 2
b110 ,
b110 .
#50000
1'
0%
0(
b1010 /
10
b101 *
b101 2
b111 ,
b111 .
#60000
0$
1'
00
b1001 /
11
b110 *
b110 2
b101 ,
b101 .
#70000
1%
0'
1#
1$
b1000 /
10
b111 *
b111 2
b100 ,
b100 .
#80000
0#
0$
0%
0"
00
01
b111 /
03
14
b1000 *
b1000 2
b1100 ,
b1100 .
#90000
1$
b110 /
10
b1001 *
b1001 2
b1101 ,
b1101 .
#100000
0$
0%
1"
0(
00
b101 /
11
b1010 *
b1010 2
b1111 ,
b1111 .
#110000
1%
1(
1$
1#
b100 /
10
b1011 *
b1011 2
b1110 ,
b1110 .
#120000
1&
0$
0%
0(
0"
00
01
b11 /
13
b1100 *
b1100 2
b1010 ,
b1010 .
#130000
0&
1$
b10 /
10
b1101 *
b1101 2
b1011 ,
b1011 .
#140000
1%
1(
0#
0'
00
b1 /
11
b1110 *
b1110 2
b1001 ,
b1001 .
#150000
1'
0(
0%
b0 /
10
b1111 *
b1111 2
b1000 ,
b1000 .
